{
	"api_path_development":"https://cbs.wappsystem.com/dev/",
	"api_path_production":"https://cbs.wappsystem.com/pro/",
	"api_path_woolcock":"https://rt.woolcock.org.au/",
	"default_production":"No",
	"panels":{
        "website":		{"url":"",                          	"modules":["website/index.json"]},
		"pages":       	{"url":"pages/panel.html", 				"modules":["pages|index.json"]},
		"portal":		{"url":"portal/panel.html",         	"modules":[
			"about/index.json",
            "purchase-order-request/index.json",
            "purchase-order-approval/index.json",
			"purchase-order-process/index.json",
			"business-management/index.json",
            "help/index.json",
			"marketing-department/index.json"
        ]},
		"blog":	        					{"url":"blog/panel.html",   						"modules":["blog/index.json"]},
		"bookkeeping":						{"url":"bookkeeping/panel.html",					"modules":["bookkeeping/index.json"]},
		"car-booking":						{"url":"car-booking/panel.html",					"modules":["car-booking/index.json"]},
		"clinic-online-questionnaire-01":	{"url":"clinic-online-questionnaire-01/panel.html",	"modules":["clinic-online-questionnaire-01/index.json"]},
		"dynamic":            				{"url":"dynamic/panel.html",						"modules":["dynamic/index.json"]},
		"equipment-booking":				{"url":"equipment-booking/panel.html",  			"modules":["equipment-booking/index.json"]},
		"fitness":							{"url":"fitness/panel.html",						"modules":["fitness/index.json"]},
		"incident-reporting":				{"url":"incident-reporting/panel.html",				"modules":["incident-reporting/index.json"]},
		"invoice":	    					{"url":"invoice/panel.html",						"modules":["invoice/index.json"]},
		"medical-practitioner":				{"url":"medical-practitioner/panel.html",			"modules":["medical-practitioner/index.json"]},
		"module-example":	    			{"url":"distributed-module-testing/panel.html",   	"modules":["distributed-module-testing/index.json"]},
		"panel_shadow_dom":     			{"url":"shadow-dom/panel.html",						"modules":["shadow-dom/index.json"]},
		"ppm":								{"url":"ppm/panel.html",  							"modules":["ppm/index.json"]},
		"restaurant":						{"url":"restaurant/panel.html",  					"modules":["restaurant/index.json"]},
		"room-booking":						{"url":"room-booking/panel.html",					"modules":["room-booking/index.json"]},
		"staff-management":	        		{"url":"staff-management/panel.html",				"modules":["staff-management/index.json"]},
        "staff-management-child":			{"url":"staff-management/staff-child-panel.html",	"modules":["staff-management/index.json"]},
		"staff-my-records":	        		{"url":"staff-my-records/panel.html",				"modules":["staff-my-records/index.json"]},
		"static":            				{"url":"static/panel.html",							"modules":["static/index.json"]},
		"template":		        			{"url":"template/panel.html",   					"modules":[]},
		"under-development-and-test":		{"url":"under-development-and-test/panel.html",		"modules":["under-development-and-test/index.json"]},
		"woolworths-credit-card":			{"url":"woolworths-credit-card/panel.html",			"modules":["woolworths-credit-card/index.json"]},
		"workplace-inspection":				{"url":"workplace-inspection/panel.html",			"modules":["workplace-inspection/index.json"]},
        "team-event-calendar":				{"url":"team-event-calendar/panel.html",			"modules":["team-event-calendar/index.json"]},
		"wk-it":                     		{"url":"wk-it/management/panel.html",		        "modules":["wk-it|management/index.json"]},
		"service-booking":             		{"url":"service-booking/panel.html",		        "modules":["service-booking/index.json"]},
		"sales-tracking":             		{"url":"sales-tracking/panel.html",		        	"modules":["sales-tracking/index.json"]},
		"document-collaboration-tracking": 	{"url":"document-collaboration-tracking/panel.html","modules":["document-collaboration-tracking/index.json"]},
        "form-and-data-examples":           {"url":"form-and-data-examples/panel.html", 		"modules":["form-and-data-examples|index.json"]},
		"report-examples":           		{"url":"report-examples/panel.html", 					"modules":["report-examples|index.json"]},
		"isleephealth-task":           		{"url":"isleephealth/task/panel.html", 					"modules":["isleephealth/task/index.json"]},
		"panel-initial":					{"url":"isleephealth-patients-portal/initial/panel.html","modules":["isleephealth-patients-portal/initial/index.json"]},

		"clinical-trials-participant-visit-booking":{"url":"clinical-trials-participant-visit-booking/panel.html","modules":["clinical-trials-participant-visit-booking/index.json"]},
		"research-volunteer-registration":	{"url":"research-volunteer-registration/panel.html",										"modules":["https://volunteer-database.rt.org.au|configurations/main.json"]},
		"research-volunteer-management":	{"url":"research-volunteer-management/panel.html",
			"modules":[
				"https://volunteer-database-management.rt.org.au|modules/research-projects/module.json",
				"https://volunteer-database-management.rt.org.au|modules/admin/module.json",
				"https://volunteer-database-management.rt.org.au|modules/project/module.json",
				"https://volunteer-database-management.rt.org.au|modules/project-approval/module.json",
				"https://volunteer-database-management.rt.org.au|modules/others/module.json",
				"https://volunteer-database-management.rt.org.au|modules/builder/module.json"
		]},

		"panel_nightstudy":     	{"url":"https://nightstudy.rt.org.au/modules/panel/main.html",										"modules":["https://nightstudy.rt.org.au|configurations/main.json","https://nightstudy.rt.org.au|configurations/task.json"]},

		"amazes":  					{"url":"amazes/panel/main.html",	"modules":["amazes|participant-and-others/index.json","amazes|edc/index.json"]},
        "sfix":                     {"url":"sfix/modules/panel/sfix.html",		                        "modules":["sfix|modules/participant-and-others/module.json","sfix|modules/edc/module.json"]},
        "sfix-child":               {"url":"sfix/modules/panel/sfix.child.html",                        "modules":["sfix|modules/participant-and-others/module.json","sfix|modules/edc/module.json"]},
        "sfix-online-home":         {"url":"sfix-online-questionnaire/modules/website/task/home.html",  "modules":[]},
        "sfix-quest-panel":         {"url":"sfix-online-questionnaire/modules/panel/quest.html",        "modules":["sfix-online-questionnaire|modules/edc/module.json"]},
        "sfix-registration":        {"url":"sfix-registration/modules/website/task/home.html",		    "modules":["sfix-registration|modules/website/module.json","sfix-registration|modules/edc/module.json"]},

        "circomed":                 {"url":"circomed/modules/panel/circomed.html",						    "modules":["circomed|modules/participant-and-others/module.json","circomed|modules/edc/module.json"]},
        "circomed-child":           {"url":"circomed/modules/panel/circomed.child.html",                    "modules":["circomed|modules/participant-and-others/module.json","circomed|modules/edc/module.json"]},
        "circomed-online-home":     {"url":"circomed-online-questionnaire/modules/website/task/home.html",  "modules":[]},
        "circomed-quest-panel":     {"url":"circomed-online-questionnaire/modules/panel/quest.html",        "modules":["circomed-online-questionnaire|modules/edc/module.json"]},

        "windfarm-about":                  {"url":"windfarm-website/panel.html",                            "modules":["windfarm-website|modules/website/module.json"]},
        "windfarm-lab-study-registration": {"url":"windfarm-website/modules/website/task/lab-study.html",   "modules":["windfarm-website|modules/website/module.json","windfarm-website|modules/registration/module.json"]},
        "windfarm-home-study-registration":{"url":"windfarm-website/modules/website/task/home-study.html",  "modules":["windfarm-website|modules/website/module.json","windfarm-website|modules/registration/module.json"]},

        "windfarm-lab-study-screening-questionnaire-main":  {"url":"windfarm-lab-study-screening-questionnaire/panel/main.html",	"modules":["windfarm-lab-study-screening-questionnaire|participant-and-others/index.json","windfarm-lab-study-screening-questionnaire|edc/index.json"]},
        "windfarm-lab-study-screening-questionnaire-child": {"url":"windfarm-lab-study-screening-questionnaire/panel/child.html",	"modules":["windfarm-lab-study-screening-questionnaire|participant-and-others/index.json","windfarm-lab-study-screening-questionnaire|edc/index.json"]},
        "windfarm-lab-study-screening-questionnaire-report":{"url":"windfarm-lab-study-screening-questionnaire/report/panel.html",	"modules":["windfarm-lab-study-screening-questionnaire|report/index.json"]},

		"ron-grunstein-first-visit":{"url":"https://wappsystem.github.io/ron-grunstein/modules/first-visit/panel.html",					"modules":["https://wappsystem.github.io/ron-grunstein|modules/first-visit/module.json"]}
	}
}
